<?xml version="1.0" encoding="UTF-8"?><?xml-stylesheet href="Domeintabellen.xslt" type="text/xsl"?><sikb.lookup xmlns:xsi="http://www.w3.org/2001/XMLSchema-instance" versie="14.3.0" datum="2020-06-26"><sikb.segment_c categorie="segment" versie="5.0.0" datum="2006-11-28"><segment versie="5.0.0" datum="2006-11-28" status="Gewijzigd"><ID>1</ID><omschrijving>De locatie ligt binnen de bebouwde kom of in een stedelijk uitleggebied zoals deze bekend zijn bij de afdeling ruimtelijke ontwikkeling. De grens van de bebouwde kom is gedefinieerd in de WegenVerkeersWet. Ook ligt de locatie niet op een bedrijven-/ industrieterrein: "een in bedrijf zijnde en blijvende bedrijfslocatie" zoals ook geformuleerd onder de voorwaarden van de bedrijvenregeling</omschrijving><waarde>Stedelijk gebied</waarde></segment><segment versie="5.0.0" datum="2006-11-28" status="Gewijzigd"><ID>2</ID><omschrijving>De locatie ligt buiten de bebouwde kom of een stedelijk uitleggebied zoals deze bekend zijn bij de afdeling ruimtelijke ontwikkeling. De grens van de bebouwde kom is gedefinieerd in de WegenVerkeersWet. Ook ligt de locatie niet op een bedrijven-/ industrieterrein: "een in bedrijf zijnde en blijvende bedrijfslocatie" zoals ook geformuleerd onder de voorwaarden van de bedrijvenregeling</omschrijving><waarde>Landelijk gebied</waarde></segment><segment versie="5.0.0" datum="2006-11-28" status="Gewijzigd"><ID>3</ID><omschrijving>De locatie betreft een "in bedrijf zijnde en blijvende bedrijfslocatie" zoals ook geformuleerd onder de voorwaarden van de bedrijvenregeling</omschrijving><waarde>Bedrijfsterrein</waarde></segment></sikb.segment_c></sikb.lookup>